ai_metacognition/__init__.py
ai_metacognition/analyzers/__init__.py
ai_metacognition/analyzers/base.py
ai_metacognition/analyzers/counterfactual_cot.py
ai_metacognition/analyzers/model_api.py
ai_metacognition/detectors/__init__.py
ai_metacognition/detectors/base.py
ai_metacognition/detectors/observer_effect.py
ai_metacognition/detectors/sandbagging_detector.py
ai_metacognition/detectors/situational_awareness.py
ai_metacognition/integrations/__init__.py
ai_metacognition/integrations/anthropic_api.py
ai_metacognition/integrations/base.py
ai_metacognition/integrations/openai_api.py
ai_metacognition/probing/__init__.py
ai_metacognition/probing/extraction.py
ai_metacognition/probing/hooks.py
ai_metacognition/probing/probes.py
ai_metacognition/probing/vectors.py
ai_metacognition/utils/__init__.py
ai_metacognition/utils/feature_extraction.py
ai_metacognition/utils/statistical_tests.py
ai_metacognition/utils/text_processing.py
ai_metacognition/visualizations/__init__.py
ai_metacognition/visualizations/plotting.py
ai_metacognition_toolkit-0.3.0.dist-info/licenses/LICENSE
ai_metacognition_toolkit-0.3.0.dist-info/METADATA
ai_metacognition_toolkit-0.3.0.dist-info/WHEEL
ai_metacognition_toolkit-0.3.0.dist-info/top_level.txt
ai_metacognition_toolkit-0.3.0.dist-info/RECORD
