Metadata-Version: 2.4
Name: ai-metacognition-toolkit
Version: 0.3.0
Summary: A toolkit for detecting and analyzing meta-cognitive capabilities in AI models
Author-email: Subhadip Mitra <contact@subhadipmitra.com>
License: MIT
Project-URL: Homepage, https://github.com/bassrehab/ai-metacognition-toolkit
Project-URL: Documentation, https://ai-metacognition-toolkit.subhadipmitra.com/
Project-URL: Repository, https://github.com/bassrehab/ai-metacognition-toolkit
Keywords: ai,metacognition,machine-learning,analysis,cognitive-science
Classifier: Development Status :: 3 - Alpha
Classifier: Intended Audience :: Developers
Classifier: Intended Audience :: Science/Research
Classifier: License :: OSI Approved :: MIT License
Classifier: Programming Language :: Python :: 3
Classifier: Programming Language :: Python :: 3.9
Classifier: Programming Language :: Python :: 3.10
Classifier: Programming Language :: Python :: 3.11
Classifier: Programming Language :: Python :: 3.12
Classifier: Topic :: Scientific/Engineering :: Artificial Intelligence
Requires-Python: >=3.9
License-File: LICENSE
Requires-Dist: numpy>=1.21.0
Requires-Dist: scipy>=1.7.0
Requires-Dist: pandas>=1.3.0
Requires-Dist: matplotlib>=3.4.0
Provides-Extra: dev
Requires-Dist: pytest>=7.0.0; extra == "dev"
Requires-Dist: pytest-cov>=3.0.0; extra == "dev"
Requires-Dist: black>=22.0.0; extra == "dev"
Requires-Dist: isort>=5.10.0; extra == "dev"
Requires-Dist: flake8>=4.0.0; extra == "dev"
Requires-Dist: mypy>=0.950; extra == "dev"
Dynamic: license-file
